LICENSE.txt
MANIFEST.in
README.md
_version.py
rlcluster.py
setup.py
rlcluster.egg-info/PKG-INFO
rlcluster.egg-info/SOURCES.txt
rlcluster.egg-info/dependency_links.txt
rlcluster.egg-info/not-zip-safe
rlcluster.egg-info/requires.txt
rlcluster.egg-info/top_level.txt
test/test_rlcluster.py