Metadata-Version: 2.1
Name: rlcluster
Version: 0.0.5
Summary: Implements Rodriguez-Laio clustering.
Home-page: https://bitbucket.org/claughton/rlcluster
Author: Charlie Laughton
Author-email: charles.laughton@nottingham.ac.uk
License: BSD license.
Platform: UNKNOWN
Classifier: Development Status :: 3 - Alpha
Classifier: Intended Audience :: Science/Research
Classifier: Environment :: Console
Classifier: License :: OSI Approved :: BSD License
Classifier: Programming Language :: Python
Classifier: Programming Language :: Python :: 2
Classifier: Programming Language :: Python :: 2.7
Classifier: Programming Language :: Python :: 3
Classifier: Programming Language :: Python :: 3.4
Classifier: Programming Language :: Python :: 3.5
Classifier: Topic :: Scientific/Engineering
Classifier: Operating System :: MacOS :: MacOS X
Classifier: Operating System :: POSIX
Classifier: Operating System :: Unix
License-File: LICENSE.txt
